[
  {
    "beach_id": "BPNBF230000030001",
    "name": "Gormanston Beach",
    "status": "Good",
    "result_date": "2026-06-15",
    "e_coli": "285",
    "intestinal_enterococci": "60",
    "county": "Meath",
    "local_authority": "Meath County Council",
    "updated_at": "2026-07-18T20:41:06Z"
  },
  {
    "beach_id": "BPNBF230000030001",
    "name": "Gormanston Beach",
    "status": "Excellent",
    "result_date": "2025-09-08",
    "e_coli": "183",
    "intestinal_enterococci": "52",
    "county": "Meath",
    "local_authority": "Meath County Council",
    "updated_at": "2026-07-18T20:41:06Z"
  },
  {
    "beach_id": "BPNBF230000030001",
    "name": "Gormanston Beach",
    "status": "Excellent",
    "result_date": "2025-06-16",
    "e_coli": "<10",
    "intestinal_enterococci": "<1",
    "county": "Meath",
    "local_authority": "Meath County Council",
    "updated_at": "2026-07-18T20:41:06Z"
  },
  {
    "beach_id": "BPNBF230000030001",
    "name": "Gormanston Beach",
    "status": "Excellent",
    "result_date": "2024-06-17",
    "e_coli": "<10",
    "intestinal_enterococci": "<1",
    "county": "Meath",
    "local_authority": "Meath County Council",
    "updated_at": "2026-07-18T20:41:06Z"
  }
]